{"trends":{"2009-11-13":[{"name":"#donttrytoholla","query":"#donttrytoholla"},{"name":"#wecoolandallbut","query":"#wecoolandallbut"},{"name":"Modern Warfare 2","query":"\"Modern Warfare 2\""},{"name":"#youknowyouruglyif","query":"#youknowyouruglyif"},{"name":"Glee","query":"Glee"},{"name":"#rememberdecember","query":"#rememberdecember"},{"name":"Lou Dobbs","query":"\"Lou Dobbs\""},{"name":"MW2","query":"MW2"},{"name":"Carrie Prejean","query":"\"Carrie Prejean\""},{"name":"Taylor Swift","query":"\"Taylor Swift\""},{"name":"New Moon","query":"\"New Moon\""},{"name":"#DontHackBritney","query":"#DontHackBritney"},{"name":"#oldnames","query":"#oldnames"},{"name":"Bad Romance","query":"\"Bad Romance\""},{"name":"#CelebrityPerfumes","query":"#CelebrityPerfumes"},{"name":"CMAs","query":"CMAs"},{"name":"#happybdaydara","query":"#happybdaydara"},{"name":"CNN","query":"CNN"},{"name":"Byron Scott","query":"\"Byron Scott\""},{"name":"Dollhouse","query":"Dollhouse"},{"name":"#indiemoviecliche","query":"#indiemoviecliche"},{"name":"Goodnight","query":"Goodnight"},{"name":"Chris Brown","query":"\"Chris Brown\""},{"name":"#openwebawards","query":"#openwebawards"},{"name":"Lady Gaga","query":"\"Lady Gaga\""},{"name":"Gucci Mane","query":"\"Gucci Mane\""},{"name":"Thanksgiving","query":"Thanksgiving"},{"name":"Christmas","query":"Christmas"},{"name":"#thankyoudonnie","query":"#thankyoudonnie"},{"name":"#fangsup","query":"#fangsup"}],"2009-11-14":[{"name":"#youknowyouruglyif","query":"#youknowyouruglyif"},{"name":"#aREALwife","query":"#aREALwife"},{"name":"Follow Friday","query":"\"Follow Friday\""},{"name":"#donttrytoholla","query":"#donttrytoholla"},{"name":"Modern Warfare 2","query":"\"Modern Warfare 2\""},{"name":"#05starbarbie","query":"#05starbarbie"},{"name":"TGIF","query":"TGIF"},{"name":"New Moon","query":"\"New Moon\""},{"name":"MW2","query":"MW2 OR #MW2"},{"name":"#wecoolandallbut","query":"#wecoolandallbut"},{"name":"#openwebawards","query":"#openwebawards"},{"name":"#HappyBDayDuduS","query":"#HappyBDayDuduS"},{"name":"#tommcflyontwitcam","query":"#tommcflyontwitcam"},{"name":"NASA","query":"NASA"},{"name":"#fakenumber","query":"#fakenumber"},{"name":"Jay Cutler","query":"\"Jay Cutler\""},{"name":"#rememberdecember","query":"#rememberdecember"},{"name":"Chris Brown","query":"\"Chris Brown\""},{"name":"Lady Gaga","query":"\"Lady Gaga\""},{"name":"Bears","query":"Bears"},{"name":"Vampire Diaries","query":"\"Vampire Diaries\""},{"name":"Goodnight","query":"Goodnight"},{"name":"Bad Romance","query":"\"Bad Romance\""},{"name":"Carrie Prejean","query":"\"Carrie Prejean\""},{"name":"Lakers","query":"Lakers"},{"name":"Thanksgiving","query":"Thanksgiving"},{"name":"Christmas","query":"Christmas"},{"name":"Glee","query":"Glee"},{"name":"Grey's Anatomy","query":"\"Grey's Anatomy\""},{"name":"Shannon Brown","query":"\"Shannon Brown\""}],"2009-11-15":[{"name":"#thingshaterssay","query":"#thingshaterssay"},{"name":"H&M","query":"H&M"},{"name":"#WorldDiabetesDay","query":"#WorldDiabetesDay"},{"name":"#funnymartinmoment","query":"#funnymartinmoment"},{"name":"Jedward","query":"Jedward"},{"name":"Modern Warfare 2","query":"\"Modern Warfare 2\""},{"name":"New Moon","query":"\"New Moon\""},{"name":"#fakenumber","query":"#fakenumber"},{"name":"#arealwife","query":"#arealwife"},{"name":"#openwebawards","query":"#openwebawards"},{"name":"#allwhites","query":"#allwhites"},{"name":"MW2","query":"MW2"},{"name":"#youknowyouruglyif","query":"#youknowyouruglyif"},{"name":"Follow Friday","query":"\"Follow Friday\""},{"name":"Cotto","query":"Cotto"},{"name":"X Factor","query":"\"X Factor\""},{"name":"Lakers","query":"Lakers"},{"name":"#followS4C","query":"#followS4C"},{"name":"#NicksSimpleWins","query":"#NicksSimpleWins"},{"name":"#stevens","query":"#stevens"},{"name":"Jimmy Choo","query":"\"Jimmy Choo\""},{"name":"Goodnight","query":"Goodnight"},{"name":"Christmas","query":"Christmas"},{"name":"Lady Gaga","query":"\"Lady Gaga\""},{"name":"#ToiletBandnames","query":"#ToiletBandnames"},{"name":"New Zealand","query":"\"New Zealand\""},{"name":"Paranormal Activity","query":"\"Paranormal Activity\""},{"name":"Pacquiao","query":"Pacquiao"},{"name":"bad romance","query":"\"bad romance\""},{"name":"Justin Bieber","query":"\"Justin Bieber\""}],"2009-11-09":[{"name":"Jedward","query":"Jedward"},{"name":"SNL","query":"SNL"},{"name":"#hcr","query":"#hcr"},{"name":"Jaebum","query":"Jaebum"},{"name":"Taylor Swift","query":"\"Taylor Swift\""},{"name":"New Moon","query":"\"New Moon\""},{"name":"Chelsea","query":"Chelsea"},{"name":"Stupak","query":"Stupak"},{"name":"#Rihannasforehead","query":"#Rihannasforehead"},{"name":"Paranormal Activity","query":"\"Paranormal Activity\""},{"name":"Fedor","query":"Fedor"},{"name":"#goodtimes","query":"#goodtimes"},{"name":"SHINee","query":"SHINee"},{"name":"NFL","query":"NFL OR #NFL"},{"name":"X Factor","query":"\"X Factor\""},{"name":"Fort Hood","query":"\"Fort Hood\""},{"name":"X-Factor","query":"X-Factor"},{"name":"Lucie","query":"Lucie"},{"name":"Bad Romance","query":"\"Bad Romance\""},{"name":"Simon Cowell","query":"\"Simon Cowell\""},{"name":"This Is It","query":"\"This Is It\""},{"name":"C-Span","query":"C-Span"},{"name":"Giants","query":"Giants OR #Giants"},{"name":"Goodnight","query":"Goodnight"},{"name":"Inkigayo","query":"Inkigayo"},{"name":"Nick","query":"Nick"},{"name":"Health Care Reform","query":"\"Health Care Reform\""},{"name":"Hurricane Ida","query":"\"Hurricane Ida\""},{"name":"Bears","query":"Bears"},{"name":"Droid","query":"Droid"}],"2009-11-10":[{"name":"#MusicMonday","query":"#MusicMonday"},{"name":"#worldsthinnestbooks","query":"#worldsthinnestbooks"},{"name":"#goodtimes","query":"#goodtimes"},{"name":"#MM","query":"#MM"},{"name":"Berlin Wall","query":"\"Berlin Wall\""},{"name":"Modern Warfare 2","query":"\"Modern Warfare 2\""},{"name":"#famoushoodquotes","query":"#famoushoodquotes"},{"name":"MW2","query":"MW2 OR #MW2"},{"name":"New Moon","query":"\"New Moon\""},{"name":"Jedward","query":"Jedward"},{"name":"#2wordsliberalshate","query":"#2wordsliberalshate"},{"name":"Eagles","query":"Eagles"},{"name":"Mad Men","query":"\"Mad Men\""},{"name":"Fort Hood","query":"\"Fort Hood\""},{"name":"Katt Williams","query":"\"Katt Williams\""},{"name":"Goodnight","query":"Goodnight"},{"name":"#whatrepublicanswant","query":"#whatrepublicanswant"},{"name":"Hurricane Ida","query":"\"Hurricane Ida\" OR Ida"},{"name":"#attentiondeficit","query":"#attentiondeficit"},{"name":"Giants","query":"Giants"},{"name":"#madmen","query":"#madmen"},{"name":"Bad Romance","query":"\"Bad Romance\""},{"name":"Khloe","query":"Khloe"},{"name":"AdMob","query":"AdMob"},{"name":"Firefox","query":"Firefox"},{"name":"Cowboys","query":"Cowboys"},{"name":"Kardashians","query":"Kardashians"},{"name":"Christmas","query":"Christmas"},{"name":"Droid","query":"Droid"},{"name":"#WhoDat","query":"#WhoDat"}],"2009-11-11":[{"name":"#bestfeeling","query":"#bestfeeling"},{"name":"#worstfeeling","query":"#worstfeeling"},{"name":"Modern Warfare 2","query":"\"Modern Warfare 2\""},{"name":"#FamousHoodQuotes","query":"#FamousHoodQuotes"},{"name":"MW2","query":"MW2 OR #mw2"},{"name":"#MusicMonday","query":"#MusicMonday"},{"name":"Bad Romance","query":"\"Bad Romance\""},{"name":"#Overyou","query":"#Overyou"},{"name":"#attentiondeficit","query":"#attentiondeficit"},{"name":"Sesame Street","query":"\"Sesame Street\""},{"name":"#mm","query":"#mm"},{"name":"New Moon","query":"\"New Moon\""},{"name":"CoD","query":"CoD"},{"name":"Fort Hood","query":"\"Fort Hood\""},{"name":"Them Crooked","query":"\"Them Crooked\""},{"name":"LinkedIn","query":"LinkedIn"},{"name":"#worldsthinnestbooks","query":"#worldsthinnestbooks"},{"name":"#Somayareeceis","query":"#Somayareeceis"},{"name":"Berlin Wall","query":"\"Berlin Wall\""},{"name":"Lopez Tonight","query":"\"Lopez Tonight\""},{"name":"Lady Gaga","query":"\"Lady Gaga\" OR GaGa"},{"name":"Goodnight","query":"Goodnight"},{"name":"Steelers","query":"Steelers"},{"name":"#goodtimes","query":"#goodtimes"},{"name":"#openwebawards","query":"#openwebawards"},{"name":"Christmas","query":"Christmas"},{"name":"Kareem Abdul-Jabbar","query":"\"Kareem Abdul-Jabbar\""},{"name":"Droid","query":"Droid"},{"name":"Gossip Girl","query":"\"Gossip Girl\""},{"name":"#HappybdayAndySkib","query":"#HappybdayAndySkib"}],"2009-11-12":[{"name":"#celebrityperfumes","query":"#celebrityperfumes"},{"name":"#bestfeeling","query":"#bestfeeling"},{"name":"Happy Veterans Day","query":"\"Happy Veterans Day\" OR \"Veterans Day\""},{"name":"Modern Warfare 2","query":"\"Modern Warfare 2\""},{"name":"#worstfeeling","query":"#worstfeeling"},{"name":"MW2","query":"MW2"},{"name":"Bad Romance","query":"\"Bad Romance\""},{"name":"#WeCoolAndAllBut","query":"#WeCoolAndAllBut"},{"name":"#2minutesilence","query":"#2minutesilence"},{"name":"#oldnames","query":"#oldnames"},{"name":"Dollhouse","query":"Dollhouse OR #dollhouse"},{"name":"New Moon","query":"\"New Moon\""},{"name":"#OverYou","query":"#OverYou"},{"name":"Lady Gaga","query":"\"Lady Gaga\""},{"name":"John Allen Muhammad","query":"\"John Allen Muhammad\""},{"name":"Remembrance Day","query":"\"Remembrance Day\" OR \"Veterans Day\""},{"name":"#VeteransDay","query":"#VeteransDay"},{"name":"Vets","query":"Vets"},{"name":"DC Sniper","query":"\"DC Sniper\""},{"name":"Goodnight","query":"Goodnight"},{"name":"FOX","query":"FOX"},{"name":"Lou Dobbs","query":"\"Lou Dobbs\" OR Dobbs"},{"name":"Christmas","query":"Christmas"},{"name":"Fort Hood","query":"\"Fort Hood\""},{"name":"Glee","query":"Glee OR #Glee"},{"name":"Thanksgiving","query":"Thanksgiving"},{"name":"#JasonMrazChat","query":"#JasonMrazChat"},{"name":"LinkedIn","query":"LinkedIn"},{"name":"#taeyang","query":"#taeyang"},{"name":"COD","query":"COD"}]},"as_of":1258412676}